MANIFEST.in
README.md
setup.py
bottle_api_json_formatting/__init__.py
bottle_api_json_formatting/bottle_api_json_formatting.py
bottle_api_json_formatting/test_app.py
bottle_api_json_formatting.egg-info/PKG-INFO
bottle_api_json_formatting.egg-info/SOURCES.txt
bottle_api_json_formatting.egg-info/dependency_links.txt
bottle_api_json_formatting.egg-info/requires.txt
bottle_api_json_formatting.egg-info/top_level.txt