Metadata-Version: 1.0
Name: bottle-api-json-formatting
Version: 0.0.8
Summary: A bottle plugin to json format standard and error responses.         Intended for REST APIs.
Home-page: http://www.bustleandflurry.com
Author: Aron Bartling
Author-email: aron@bustleandflurry.com
License: MIT
Keywords: Bottle Plugin JSON
Platform: UNKNOWN
Classifier: Development Status :: 3 - Alpha
Classifier: Topic :: Internet
Classifier: Environment :: Plugins
Classifier: Framework :: Bottle
Classifier: License :: OSI Approved :: MIT License
Classifier: Intended Audience :: Developers
